dimsync/__init__.py
dimsync/main.py
dimsync-0.1.23.dist-info/LICENSE
dimsync-0.1.23.dist-info/METADATA
dimsync-0.1.23.dist-info/WHEEL
dimsync-0.1.23.dist-info/entry_points.txt
dimsync-0.1.23.dist-info/top_level.txt
dimsync-0.1.23.dist-info/RECORD
